[
    {
        "date": "2023-07-21",
        "events": [
            "odpady zmieszane",
            "odpady BIO"
        ]
    },
    {
        "date": "2023-08-04",
        "events": [
            "odpady zmieszane",
            "odpady BIO"
        ]
    },
    {
        "date": "2023-08-18",
        "events": [
            "odpady zmieszane",
            "odpady BIO"
        ]
    },
    {
        "date": "2023-09-01",
        "events": [
            "odpady zmieszane",
            "odpady BIO"
        ]
    },
    {
        "date": "2023-09-15",
        "events": [
            "odpady zmieszane",
            "odpady BIO"
        ]
    },
    {
        "date": "2023-09-29",
        "events": [
            "odpady zmieszane",
            "odpady BIO"
        ]
    },
    {
        "date": "2023-10-13",
        "events": [
            "odpady zmieszane",
            "odpady BIO"
        ]
    },
    {
        "date": "2023-10-27",
        "events": [
            "odpady zmieszane",
            "odpady BIO"
        ]
    },
    {
        "date": "2023-11-03",
        "events": [
            "odpady BIO"
        ]
    },
    {
        "date": "2023-11-10",
        "events": [
            "odpady zmieszane"
        ]
    },
    {
        "date": "2023-11-24",
        "events": [
            "odpady zmieszane"
        ]
    },
    {
        "date": "2023-12-01",
        "events": [
            "odpady BIO"
        ]
    },
    {
        "date": "2023-12-08",
        "events": [
            "odpady zmieszane"
        ]
    },
    {
        "date": "2023-12-22",
        "events": [
            "odpady zmieszane"
        ]
    },
    {
        "date": "2023-08-07",
        "events": [
            "odpady segregowane"
        ]
    },
    {
        "date": "2023-09-04",
        "events": [
            "odpady segregowane"
        ]
    },
    {
        "date": "2023-10-02",
        "events": [
            "odpady segregowane"
        ]
    },
    {
        "date": "2023-11-06",
        "events": [
            "odpady segregowane"
        ]
    },
    {
        "date": "2023-12-04",
        "events": [
            "odpady segregowane"
        ]
    },
    {
        "date": "2023-11-03",
        "events": [
            "odpady wielogabarytowe",
            "zużyty sprzęt RTV i AGD"
        ]
    }
]